{
  "item_id": "processed_0e6fa3c4-c7d1-4ded-a204-2d9ace52bd53",
  "image_path": "c:\\Users\\Francis Arroyo\\Documents\\BARYONYX\\static\\uploads\\659066d5-70ce-45f6-8839-b2ed6c19d5be_479542156_603763932457468_3208412858055879828_n.jpg",
  "detected_objects": [
    {
      "class": "mouse",
      "confidence": 0.794071614742279,
      "original_confidence": 0.794071614742279,
      "box": [
        362.7370910644531,
        366.76434326171875,
        1976.5157470703125,
        1220.233154296875
      ]
    },
    {
      "class": "cell phone",
      "confidence": 0.5864161491394043,
      "original_confidence": 0.5614161491394043,
      "box": [
        346.91705322265625,
        347.1161193847656,
        1558.1805419921875,
        1187.16162109375
      ],
      "color": {
        "B": 65,
        "G": 67,
        "R": 80
      },
      "features": [
        "dual_camera_detected",
        "fingerprint_sensor_detected"
      ]
    }
  ],
  "user_labels": [],
  "auto_labels": [
    {
      "class": "mouse",
      "confidence": 0.794071614742279,
      "original_confidence": 0.794071614742279,
      "box": [
        362.7370910644531,
        366.76434326171875,
        1976.5157470703125,
        1220.233154296875
      ]
    },
    {
      "class": "cell phone",
      "confidence": 0.5864161491394043,
      "original_confidence": 0.5614161491394043,
      "box": [
        346.91705322265625,
        347.1161193847656,
        1558.1805419921875,
        1187.16162109375
      ],
      "color": {
        "B": 65,
        "G": 67,
        "R": 80
      },
      "features": [
        "dual_camera_detected",
        "fingerprint_sensor_detected"
      ]
    }
  ],
  "category": "other",
  "status": "found",
  "timestamp": "2025-09-20T08:28:59.403923",
  "source": "user_upload"
}